<?xml version="1.0" encoding="utf-8"?>
<Solution xmlns="http://schemas.microsoft.com/sharepoint/" SolutionId="27614e78-08e5-4172-98d7-156dd61d5858" SharePointProductVersion="15.0">
  <Assemblies>
    <Assembly Location="CAMLProject.dll" DeploymentTarget="GlobalAssemblyCache">
      <SafeControls>
        <SafeControl Assembly="CAMLProject, Version=1.0.0.0, Culture=neutral, PublicKeyToken=d8d8d4847fcc218a" Namespace="CAMLProject.WebPart1" TypeName="*" />
      </SafeControls>
    </Assembly>
  </Assemblies>
  <FeatureManifests>
    <FeatureManifest Location="CAMLProject_Feature1\Feature.xml" />
  </FeatureManifests>
</Solution>
